{
    "info": {
        "description": "ISAT",
        "folder": "C:/my_project/dataset/sy_dataset/train/dataset_pre",
        "name": "142.png",
        "width": 512,
        "height": 512,
        "depth": 3,
        "note": ""
    },
    "objects": [
        {
            "category": "L3",
            "group": "",
            "segmentation": [
                [
                    181,
                    217
                ],
                [
                    175,
                    218
                ],
                [
                    170,
                    219
                ],
                [
                    167,
                    220
                ],
                [
                    162,
                    225
                ],
                [
                    159,
                    232
                ],
                [
                    155,
                    238
                ],
                [
                    151,
                    242
                ],
                [
                    146,
                    246
                ],
                [
                    142,
                    248
                ],
                [
                    140,
                    250
                ],
                [
                    140,
                    251
                ],
                [
                    139,
                    252
                ],
                [
                    131,
                    259
                ],
                [
                    128,
                    263
                ],
                [
                    125,
                    269
                ],
                [
                    124,
                    272
                ],
                [
                    123,
                    275
                ],
                [
                    122,
                    281
                ],
                [
                    122,
                    293
                ],
                [
                    123,
                    297
                ],
                [
                    124,
                    300
                ],
                [
                    127,
                    307
                ],
                [
                    128,
                    309
                ],
                [
                    130,
                    309
                ],
                [
                    136,
                    307
                ],
                [
                    138,
                    304
                ],
                [
                    143,
                    301
                ],
                [
                    144,
                    298
                ],
                [
                    146,
                    296
                ],
                [
                    148,
                    296
                ],
                [
                    152,
                    293
                ],
                [
                    157,
                    293
                ],
                [
                    160,
                    292
                ],
                [
                    165,
                    289
                ],
                [
                    170,
                    288
                ],
                [
                    172,
                    287
                ],
                [
                    176,
                    283
                ],
                [
                    176,
                    281
                ],
                [
                    181,
                    276
                ],
                [
                    184,
                    271
                ],
                [
                    185,
                    266
                ],
                [
                    188,
                    263
                ],
                [
                    188,
                    261
                ],
                [
                    191,
                    258
                ],
                [
                    192,
                    256
                ],
                [
                    192,
                    247
                ],
                [
                    191,
                    246
                ],
                [
                    191,
                    238
                ],
                [
                    192,
                    225
                ],
                [
                    194,
                    223
                ],
                [
                    195,
                    221
                ],
                [
                    192,
                    219
                ],
                [
                    190,
                    218
                ],
                [
                    187,
                    218
                ],
                [
                    186,
                    217
                ],
                [
                    184,
                    217
                ]
            ],
            "area": 3771.0,
            "layer": 1.0,
            "bbox": [
                122.0,
                217.0,
                195.0,
                309.0
            ],
            "iscrowd": 0,
            "note": ""
        },
        {
            "category": "R3",
            "group": "",
            "segmentation": [
                [
                    315,
                    224
                ],
                [
                    313,
                    225
                ],
                [
                    313,
                    227
                ],
                [
                    314,
                    228
                ],
                [
                    314,
                    231
                ],
                [
                    316,
                    235
                ],
                [
                    317,
                    240
                ],
                [
                    317,
                    261
                ],
                [
                    319,
                    264
                ],
                [
                    319,
                    271
                ],
                [
                    317,
                    275
                ],
                [
                    317,
                    280
                ],
                [
                    319,
                    284
                ],
                [
                    319,
                    296
                ],
                [
                    318,
                    299
                ],
                [
                    314,
                    304
                ],
                [
                    314,
                    306
                ],
                [
                    312,
                    308
                ],
                [
                    312,
                    313
                ],
                [
                    313,
                    315
                ],
                [
                    317,
                    319
                ],
                [
                    319,
                    320
                ],
                [
                    328,
                    321
                ],
                [
                    332,
                    323
                ],
                [
                    339,
                    323
                ],
                [
                    341,
                    323
                ],
                [
                    344,
                    321
                ],
                [
                    350,
                    320
                ],
                [
                    372,
                    320
                ],
                [
                    375,
                    319
                ],
                [
                    378,
                    317
                ],
                [
                    379,
                    315
                ],
                [
                    380,
                    312
                ],
                [
                    381,
                    304
                ],
                [
                    381,
                    297
                ],
                [
                    380,
                    291
                ],
                [
                    379,
                    288
                ],
                [
                    378,
                    285
                ],
                [
                    375,
                    279
                ],
                [
                    373,
                    276
                ],
                [
                    371,
                    273
                ],
                [
                    366,
                    266
                ],
                [
                    355,
                    255
                ],
                [
                    348,
                    250
                ],
                [
                    343,
                    245
                ],
                [
                    336,
                    235
                ],
                [
                    333,
                    232
                ],
                [
                    330,
                    231
                ],
                [
                    328,
                    231
                ],
                [
                    325,
                    230
                ],
                [
                    322,
                    228
                ],
                [
                    318,
                    224
                ]
            ],
            "area": 4457.5,
            "layer": 2.0,
            "bbox": [
                312.0,
                224.0,
                381.0,
                323.0
            ],
            "iscrowd": 0,
            "note": ""
        },
        {
            "category": "S",
            "group": "",
            "segmentation": [
                [
                    244,
                    191
                ],
                [
                    238,
                    192
                ],
                [
                    234,
                    193
                ],
                [
                    228,
                    196
                ],
                [
                    224,
                    200
                ],
                [
                    220,
                    202
                ],
                [
                    215,
                    207
                ],
                [
                    214,
                    207
                ],
                [
                    210,
                    211
                ],
                [
                    207,
                    215
                ],
                [
                    205,
                    218
                ],
                [
                    203,
                    221
                ],
                [
                    202,
                    223
                ],
                [
                    201,
                    225
                ],
                [
                    198,
                    233
                ],
                [
                    197,
                    237
                ],
                [
                    197,
                    243
                ],
                [
                    199,
                    252
                ],
                [
                    200,
                    255
                ],
                [
                    201,
                    257
                ],
                [
                    203,
                    260
                ],
                [
                    216,
                    273
                ],
                [
                    219,
                    275
                ],
                [
                    221,
                    276
                ],
                [
                    224,
                    277
                ],
                [
                    239,
                    277
                ],
                [
                    246,
                    275
                ],
                [
                    251,
                    275
                ],
                [
                    256,
                    276
                ],
                [
                    259,
                    277
                ],
                [
                    264,
                    279
                ],
                [
                    271,
                    283
                ],
                [
                    276,
                    284
                ],
                [
                    280,
                    284
                ],
                [
                    288,
                    283
                ],
                [
                    291,
                    282
                ],
                [
                    298,
                    279
                ],
                [
                    307,
                    275
                ],
                [
                    311,
                    271
                ],
                [
                    312,
                    269
                ],
                [
                    312,
                    261
                ],
                [
                    314,
                    253
                ],
                [
                    314,
                    239
                ],
                [
                    313,
                    235
                ],
                [
                    307,
                    220
                ],
                [
                    306,
                    218
                ],
                [
                    305,
                    216
                ],
                [
                    303,
                    213
                ],
                [
                    301,
                    210
                ],
                [
                    293,
                    202
                ],
                [
                    290,
                    200
                ],
                [
                    288,
                    199
                ],
                [
                    281,
                    198
                ],
                [
                    276,
                    196
                ],
                [
                    268,
                    192
                ],
                [
                    257,
                    191
                ]
            ],
            "area": 8533.5,
            "layer": 3.0,
            "bbox": [
                197.0,
                191.0,
                314.0,
                284.0
            ],
            "iscrowd": 0,
            "note": ""
        },
        {
            "category": "L",
            "group": "",
            "segmentation": [
                [
                    198,
                    297
                ],
                [
                    195,
                    299
                ],
                [
                    187,
                    302
                ],
                [
                    172,
                    305
                ],
                [
                    165,
                    303
                ],
                [
                    152,
                    303
                ],
                [
                    138,
                    311
                ],
                [
                    132,
                    326
                ],
                [
                    126,
                    329
                ],
                [
                    115,
                    335
                ],
                [
                    104,
                    340
                ],
                [
                    87,
                    349
                ],
                [
                    83,
                    354
                ],
                [
                    85,
                    363
                ],
                [
                    95,
                    374
                ],
                [
                    114,
                    386
                ],
                [
                    124,
                    392
                ],
                [
                    140,
                    397
                ],
                [
                    154,
                    402
                ],
                [
                    165,
                    406
                ],
                [
                    183,
                    408
                ],
                [
                    199,
                    407
                ],
                [
                    210,
                    404
                ],
                [
                    217,
                    397
                ],
                [
                    223,
                    378
                ],
                [
                    228,
                    365
                ],
                [
                    231,
                    351
                ],
                [
                    229,
                    336
                ],
                [
                    223,
                    328
                ],
                [
                    212,
                    328
                ],
                [
                    198,
                    326
                ],
                [
                    198,
                    313
                ],
                [
                    198,
                    313
                ]
            ],
            "area": 10625.218735725142,
            "layer": 4.0,
            "bbox": [
                83.27524513220877,
                296.66806078349373,
                231.23751103675826,
                408.1974069427019
            ],
            "iscrowd": 0,
            "note": ""
        },
        {
            "category": "R",
            "group": "",
            "segmentation": [
                [
                    289,
                    308
                ],
                [
                    292,
                    320
                ],
                [
                    292,
                    325
                ],
                [
                    290,
                    329
                ],
                [
                    287,
                    332
                ],
                [
                    281,
                    333
                ],
                [
                    276,
                    334
                ],
                [
                    267,
                    338
                ],
                [
                    259,
                    344
                ],
                [
                    252,
                    356
                ],
                [
                    246,
                    368
                ],
                [
                    245,
                    377
                ],
                [
                    252,
                    394
                ],
                [
                    262,
                    403
                ],
                [
                    273,
                    408
                ],
                [
                    284,
                    413
                ],
                [
                    305,
                    417
                ],
                [
                    316,
                    417
                ],
                [
                    341,
                    414
                ],
                [
                    348,
                    412
                ],
                [
                    354,
                    410
                ],
                [
                    367,
                    406
                ],
                [
                    375,
                    400
                ],
                [
                    383,
                    396
                ],
                [
                    401,
                    381
                ],
                [
                    411,
                    372
                ],
                [
                    414,
                    368
                ],
                [
                    396,
                    362
                ],
                [
                    383,
                    355
                ],
                [
                    375,
                    348
                ],
                [
                    356,
                    340
                ],
                [
                    342,
                    337
                ],
                [
                    329,
                    331
                ],
                [
                    313,
                    319
                ],
                [
                    305,
                    312
                ],
                [
                    305,
                    312
                ]
            ],
            "area": 10841.756486482322,
            "layer": 5.0,
            "bbox": [
                244.62103257586324,
                307.8209953994145,
                414.35382685069015,
                417.4915191226359
            ],
            "iscrowd": 0,
            "note": ""
        },
        {
            "category": "L1",
            "group": "",
            "segmentation": [
                [
                    200,
                    297
                ],
                [
                    195,
                    302
                ],
                [
                    190,
                    312
                ],
                [
                    185,
                    325
                ],
                [
                    183,
                    334
                ],
                [
                    179,
                    350
                ],
                [
                    179,
                    369
                ],
                [
                    180,
                    385
                ],
                [
                    185,
                    396
                ],
                [
                    196,
                    400
                ],
                [
                    204,
                    399
                ],
                [
                    198,
                    403
                ],
                [
                    183,
                    404
                ],
                [
                    173,
                    404
                ],
                [
                    159,
                    404
                ],
                [
                    148,
                    402
                ],
                [
                    140,
                    399
                ],
                [
                    123,
                    395
                ],
                [
                    115,
                    391
                ],
                [
                    105,
                    386
                ],
                [
                    94,
                    377
                ],
                [
                    84,
                    368
                ],
                [
                    80,
                    358
                ],
                [
                    80,
                    352
                ],
                [
                    90,
                    345
                ],
                [
                    117,
                    339
                ],
                [
                    127,
                    335
                ],
                [
                    136,
                    325
                ],
                [
                    147,
                    318
                ],
                [
                    159,
                    311
                ],
                [
                    171,
                    306
                ],
                [
                    171,
                    306
                ]
            ],
            "area": 6911.2572397431395,
            "layer": 6.0,
            "bbox": [
                79.76578837306567,
                296.5788373065663,
                203.96486825595986,
                404.18235048097034
            ],
            "iscrowd": 0,
            "note": ""
        },
        {
            "category": "L2",
            "group": "",
            "segmentation": [
                [
                    198,
                    301
                ],
                [
                    189,
                    304
                ],
                [
                    178,
                    311
                ],
                [
                    172,
                    323
                ],
                [
                    168,
                    342
                ],
                [
                    166,
                    368
                ],
                [
                    175,
                    392
                ],
                [
                    175,
                    398
                ],
                [
                    177,
                    402
                ],
                [
                    186,
                    404
                ],
                [
                    192,
                    403
                ],
                [
                    204,
                    400
                ],
                [
                    212,
                    394
                ],
                [
                    218,
                    390
                ],
                [
                    221,
                    386
                ],
                [
                    225,
                    381
                ],
                [
                    230,
                    370
                ],
                [
                    230,
                    362
                ],
                [
                    231,
                    352
                ],
                [
                    231,
                    343
                ],
                [
                    228,
                    338
                ],
                [
                    221,
                    328
                ],
                [
                    214,
                    326
                ],
                [
                    207,
                    322
                ],
                [
                    201,
                    319
                ],
                [
                    199,
                    313
                ],
                [
                    199,
                    313
                ]
            ],
            "area": 4719.418158257977,
            "layer": 7.0,
            "bbox": [
                166.49100794646594,
                300.8615641990799,
                230.73191133416984,
                404.18235048097034
            ],
            "iscrowd": 0,
            "note": ""
        },
        {
            "category": "R1",
            "group": "",
            "segmentation": [
                [
                    299,
                    311
                ],
                [
                    305,
                    323
                ],
                [
                    306,
                    330
                ],
                [
                    306,
                    340
                ],
                [
                    306,
                    354
                ],
                [
                    302,
                    372
                ],
                [
                    297,
                    385
                ],
                [
                    291,
                    392
                ],
                [
                    286,
                    398
                ],
                [
                    277,
                    404
                ],
                [
                    266,
                    406
                ],
                [
                    268,
                    408
                ],
                [
                    282,
                    414
                ],
                [
                    291,
                    416
                ],
                [
                    322,
                    421
                ],
                [
                    337,
                    420
                ],
                [
                    356,
                    412
                ],
                [
                    392,
                    383
                ],
                [
                    408,
                    374
                ],
                [
                    415,
                    370
                ],
                [
                    418,
                    367
                ],
                [
                    407,
                    363
                ],
                [
                    398,
                    358
                ],
                [
                    387,
                    349
                ],
                [
                    378,
                    341
                ],
                [
                    367,
                    336
                ],
                [
                    350,
                    334
                ],
                [
                    337,
                    328
                ],
                [
                    318,
                    321
                ],
                [
                    310,
                    314
                ],
                [
                    310,
                    314
                ]
            ],
            "area": 7998.005905667807,
            "layer": 8.0,
            "bbox": [
                266.064408197407,
                311.0330405687997,
                417.56587202007535,
                421.3132580510247
            ],
            "iscrowd": 0,
            "note": ""
        },
        {
            "category": "R2",
            "group": "",
            "segmentation": [
                [
                    263,
                    404
                ],
                [
                    277,
                    408
                ],
                [
                    289,
                    408
                ],
                [
                    303,
                    406
                ],
                [
                    312,
                    392
                ],
                [
                    315,
                    380
                ],
                [
                    318,
                    363
                ],
                [
                    319,
                    346
                ],
                [
                    314,
                    318
                ],
                [
                    290,
                    309
                ],
                [
                    294,
                    316
                ],
                [
                    296,
                    329
                ],
                [
                    291,
                    334
                ],
                [
                    282,
                    337
                ],
                [
                    275,
                    338
                ],
                [
                    262,
                    339
                ],
                [
                    257,
                    346
                ],
                [
                    251,
                    355
                ],
                [
                    248,
                    362
                ],
                [
                    246,
                    372
                ],
                [
                    247,
                    386
                ],
                [
                    249,
                    392
                ],
                [
                    249,
                    392
                ]
            ],
            "area": 4852.109253279879,
            "layer": 9.0,
            "bbox": [
                245.7214554579674,
                308.89167712254283,
                319.0631534922627,
                407.9297365119197
            ],
            "iscrowd": 0,
            "note": ""
        }
    ]
}