{
    "info": {
        "description": "ISAT",
        "folder": "C:/my_project/dataset/sy_dataset/train/dataset_pre",
        "name": "68.png",
        "width": 512,
        "height": 512,
        "depth": 3,
        "note": ""
    },
    "objects": [
        {
            "category": "L",
            "group": "",
            "segmentation": [
                [
                    231,
                    391
                ],
                [
                    244,
                    388
                ],
                [
                    251,
                    377
                ],
                [
                    254,
                    365
                ],
                [
                    256,
                    355
                ],
                [
                    256,
                    346
                ],
                [
                    253,
                    331
                ],
                [
                    250,
                    321
                ],
                [
                    247,
                    316
                ],
                [
                    229,
                    309
                ],
                [
                    223,
                    302
                ],
                [
                    219,
                    293
                ],
                [
                    215,
                    285
                ],
                [
                    210,
                    282
                ],
                [
                    203,
                    282
                ],
                [
                    192,
                    285
                ],
                [
                    179,
                    291
                ],
                [
                    148,
                    300
                ],
                [
                    133,
                    303
                ],
                [
                    113,
                    306
                ],
                [
                    106,
                    308
                ],
                [
                    101,
                    316
                ],
                [
                    100,
                    323
                ],
                [
                    104,
                    327
                ],
                [
                    108,
                    335
                ],
                [
                    113,
                    343
                ],
                [
                    118,
                    348
                ],
                [
                    125,
                    356
                ],
                [
                    133,
                    360
                ],
                [
                    147,
                    365
                ],
                [
                    159,
                    372
                ],
                [
                    176,
                    380
                ],
                [
                    191,
                    387
                ],
                [
                    199,
                    389
                ],
                [
                    217,
                    391
                ],
                [
                    229,
                    392
                ],
                [
                    229,
                    392
                ]
            ],
            "area": 11386.5,
            "layer": 1.0,
            "bbox": [
                100.0,
                282.0,
                256.0,
                392.0
            ],
            "iscrowd": 0,
            "note": ""
        },
        {
            "category": "R",
            "group": "",
            "segmentation": [
                [
                    285,
                    313
                ],
                [
                    283,
                    313
                ],
                [
                    275,
                    314
                ],
                [
                    270,
                    318
                ],
                [
                    268,
                    323
                ],
                [
                    266,
                    328
                ],
                [
                    266,
                    331
                ],
                [
                    265,
                    338
                ],
                [
                    265,
                    344
                ],
                [
                    265,
                    351
                ],
                [
                    265,
                    360
                ],
                [
                    266,
                    368
                ],
                [
                    269,
                    375
                ],
                [
                    272,
                    385
                ],
                [
                    276,
                    391
                ],
                [
                    283,
                    397
                ],
                [
                    291,
                    397
                ],
                [
                    301,
                    398
                ],
                [
                    310,
                    398
                ],
                [
                    318,
                    395
                ],
                [
                    327,
                    392
                ],
                [
                    341,
                    389
                ],
                [
                    351,
                    382
                ],
                [
                    357,
                    380
                ],
                [
                    368,
                    373
                ],
                [
                    387,
                    360
                ],
                [
                    398,
                    352
                ],
                [
                    411,
                    340
                ],
                [
                    418,
                    332
                ],
                [
                    418,
                    327
                ],
                [
                    398,
                    322
                ],
                [
                    389,
                    320
                ],
                [
                    376,
                    316
                ],
                [
                    366,
                    311
                ],
                [
                    356,
                    304
                ],
                [
                    347,
                    298
                ],
                [
                    334,
                    292
                ],
                [
                    326,
                    286
                ],
                [
                    319,
                    280
                ],
                [
                    312,
                    280
                ],
                [
                    311,
                    289
                ],
                [
                    310,
                    301
                ],
                [
                    291,
                    312
                ],
                [
                    295,
                    310
                ]
            ],
            "area": 10719.5,
            "layer": 2.0,
            "bbox": [
                265.0,
                280.0,
                418.0,
                398.0
            ],
            "iscrowd": 0,
            "note": ""
        },
        {
            "category": "L3",
            "group": "",
            "segmentation": [
                [
                    184,
                    202
                ],
                [
                    181,
                    203
                ],
                [
                    179,
                    204
                ],
                [
                    175,
                    207
                ],
                [
                    164,
                    218
                ],
                [
                    162,
                    219
                ],
                [
                    160,
                    220
                ],
                [
                    155,
                    221
                ],
                [
                    153,
                    222
                ],
                [
                    151,
                    223
                ],
                [
                    146,
                    227
                ],
                [
                    144,
                    229
                ],
                [
                    144,
                    230
                ],
                [
                    141,
                    233
                ],
                [
                    136,
                    242
                ],
                [
                    132,
                    251
                ],
                [
                    128,
                    256
                ],
                [
                    126,
                    259
                ],
                [
                    126,
                    264
                ],
                [
                    127,
                    267
                ],
                [
                    128,
                    269
                ],
                [
                    129,
                    271
                ],
                [
                    131,
                    274
                ],
                [
                    134,
                    277
                ],
                [
                    137,
                    279
                ],
                [
                    142,
                    281
                ],
                [
                    147,
                    285
                ],
                [
                    150,
                    286
                ],
                [
                    167,
                    286
                ],
                [
                    177,
                    285
                ],
                [
                    181,
                    284
                ],
                [
                    184,
                    283
                ],
                [
                    186,
                    282
                ],
                [
                    188,
                    281
                ],
                [
                    191,
                    279
                ],
                [
                    193,
                    277
                ],
                [
                    195,
                    274
                ],
                [
                    195,
                    272
                ],
                [
                    199,
                    267
                ],
                [
                    201,
                    262
                ],
                [
                    201,
                    256
                ],
                [
                    204,
                    253
                ],
                [
                    205,
                    251
                ],
                [
                    205,
                    244
                ],
                [
                    205,
                    232
                ],
                [
                    205,
                    228
                ],
                [
                    204,
                    226
                ],
                [
                    201,
                    224
                ],
                [
                    200,
                    222
                ],
                [
                    202,
                    219
                ],
                [
                    203,
                    216
                ],
                [
                    202,
                    212
                ],
                [
                    200,
                    210
                ],
                [
                    200,
                    209
                ],
                [
                    199,
                    208
                ],
                [
                    197,
                    206
                ],
                [
                    193,
                    203
                ],
                [
                    191,
                    202
                ]
            ],
            "area": 4703.0,
            "layer": 3.0,
            "bbox": [
                126.0,
                202.0,
                205.0,
                286.0
            ],
            "iscrowd": 0,
            "note": ""
        },
        {
            "category": "R3",
            "group": "",
            "segmentation": [
                [
                    324,
                    196
                ],
                [
                    320,
                    200
                ],
                [
                    320,
                    203
                ],
                [
                    321,
                    204
                ],
                [
                    320,
                    209
                ],
                [
                    317,
                    210
                ],
                [
                    315,
                    212
                ],
                [
                    314,
                    224
                ],
                [
                    316,
                    243
                ],
                [
                    314,
                    248
                ],
                [
                    314,
                    259
                ],
                [
                    316,
                    262
                ],
                [
                    317,
                    269
                ],
                [
                    319,
                    274
                ],
                [
                    320,
                    276
                ],
                [
                    321,
                    277
                ],
                [
                    325,
                    280
                ],
                [
                    329,
                    283
                ],
                [
                    332,
                    285
                ],
                [
                    335,
                    287
                ],
                [
                    337,
                    288
                ],
                [
                    339,
                    288
                ],
                [
                    344,
                    292
                ],
                [
                    348,
                    293
                ],
                [
                    356,
                    293
                ],
                [
                    362,
                    292
                ],
                [
                    367,
                    290
                ],
                [
                    372,
                    290
                ],
                [
                    376,
                    289
                ],
                [
                    378,
                    288
                ],
                [
                    381,
                    285
                ],
                [
                    383,
                    280
                ],
                [
                    382,
                    278
                ],
                [
                    377,
                    269
                ],
                [
                    376,
                    266
                ],
                [
                    375,
                    258
                ],
                [
                    372,
                    249
                ],
                [
                    369,
                    242
                ],
                [
                    368,
                    240
                ],
                [
                    366,
                    237
                ],
                [
                    360,
                    231
                ],
                [
                    358,
                    226
                ],
                [
                    349,
                    217
                ],
                [
                    341,
                    206
                ],
                [
                    338,
                    200
                ],
                [
                    335,
                    198
                ],
                [
                    333,
                    197
                ],
                [
                    330,
                    196
                ]
            ],
            "area": 4374.0,
            "layer": 4.0,
            "bbox": [
                314.0,
                196.0,
                383.0,
                293.0
            ],
            "iscrowd": 0,
            "note": ""
        },
        {
            "category": "L2",
            "group": "",
            "segmentation": [
                [
                    235,
                    313
                ],
                [
                    230,
                    309
                ],
                [
                    224,
                    303
                ],
                [
                    221,
                    298
                ],
                [
                    217,
                    295
                ],
                [
                    208,
                    300
                ],
                [
                    204,
                    310
                ],
                [
                    204,
                    320
                ],
                [
                    204,
                    327
                ],
                [
                    207,
                    340
                ],
                [
                    209,
                    350
                ],
                [
                    211,
                    361
                ],
                [
                    215,
                    374
                ],
                [
                    223,
                    388
                ],
                [
                    231,
                    391
                ],
                [
                    237,
                    387
                ],
                [
                    249,
                    372
                ],
                [
                    250,
                    367
                ],
                [
                    252,
                    356
                ],
                [
                    252,
                    349
                ],
                [
                    252,
                    344
                ],
                [
                    252,
                    332
                ],
                [
                    251,
                    323
                ],
                [
                    250,
                    318
                ],
                [
                    248,
                    315
                ],
                [
                    244,
                    313
                ],
                [
                    273,
                    331
                ]
            ],
            "area": 3205.0,
            "layer": 5.0,
            "bbox": [
                204.0,
                295.0,
                273.0,
                391.0
            ],
            "iscrowd": 0,
            "note": ""
        },
        {
            "category": "L1",
            "group": "",
            "segmentation": [
                [
                    251,
                    380
                ],
                [
                    248,
                    384
                ],
                [
                    240,
                    388
                ],
                [
                    232,
                    391
                ],
                [
                    222,
                    392
                ],
                [
                    215,
                    392
                ],
                [
                    208,
                    391
                ],
                [
                    200,
                    389
                ],
                [
                    194,
                    389
                ],
                [
                    186,
                    387
                ],
                [
                    175,
                    385
                ],
                [
                    170,
                    383
                ],
                [
                    163,
                    378
                ],
                [
                    160,
                    376
                ],
                [
                    153,
                    372
                ],
                [
                    148,
                    370
                ],
                [
                    141,
                    367
                ],
                [
                    136,
                    364
                ],
                [
                    131,
                    361
                ],
                [
                    123,
                    356
                ],
                [
                    114,
                    348
                ],
                [
                    107,
                    337
                ],
                [
                    102,
                    328
                ],
                [
                    101,
                    323
                ],
                [
                    101,
                    318
                ],
                [
                    106,
                    317
                ],
                [
                    120,
                    314
                ],
                [
                    128,
                    310
                ],
                [
                    141,
                    308
                ],
                [
                    150,
                    305
                ],
                [
                    170,
                    299
                ],
                [
                    185,
                    295
                ],
                [
                    199,
                    293
                ],
                [
                    206,
                    293
                ],
                [
                    205,
                    298
                ],
                [
                    204,
                    307
                ],
                [
                    203,
                    317
                ],
                [
                    203,
                    327
                ],
                [
                    205,
                    348
                ],
                [
                    206,
                    356
                ],
                [
                    208,
                    366
                ],
                [
                    209,
                    372
                ],
                [
                    212,
                    378
                ],
                [
                    216,
                    383
                ],
                [
                    218,
                    385
                ],
                [
                    226,
                    386
                ],
                [
                    233,
                    385
                ],
                [
                    237,
                    384
                ],
                [
                    237,
                    384
                ]
            ],
            "area": 7152.5,
            "layer": 6.0,
            "bbox": [
                101.0,
                293.0,
                251.0,
                392.0
            ],
            "iscrowd": 0,
            "note": ""
        },
        {
            "category": "R2",
            "group": "",
            "segmentation": [
                [
                    306,
                    313
                ],
                [
                    296,
                    310
                ],
                [
                    286,
                    310
                ],
                [
                    275,
                    313
                ],
                [
                    272,
                    317
                ],
                [
                    267,
                    323
                ],
                [
                    264,
                    336
                ],
                [
                    264,
                    356
                ],
                [
                    264,
                    366
                ],
                [
                    268,
                    377
                ],
                [
                    272,
                    386
                ],
                [
                    281,
                    392
                ],
                [
                    289,
                    389
                ],
                [
                    297,
                    383
                ],
                [
                    302,
                    373
                ],
                [
                    304,
                    357
                ],
                [
                    305,
                    343
                ],
                [
                    310,
                    328
                ],
                [
                    313,
                    322
                ],
                [
                    313,
                    316
                ],
                [
                    313,
                    311
                ],
                [
                    304,
                    314
                ],
                [
                    311,
                    316
                ]
            ],
            "area": 2992.5,
            "layer": 7.0,
            "bbox": [
                264.0,
                310.0,
                313.0,
                392.0
            ],
            "iscrowd": 0,
            "note": ""
        },
        {
            "category": "R1",
            "group": "",
            "segmentation": [
                [
                    271,
                    394
                ],
                [
                    275,
                    396
                ],
                [
                    286,
                    399
                ],
                [
                    291,
                    400
                ],
                [
                    299,
                    400
                ],
                [
                    312,
                    398
                ],
                [
                    327,
                    395
                ],
                [
                    346,
                    389
                ],
                [
                    355,
                    383
                ],
                [
                    359,
                    380
                ],
                [
                    365,
                    376
                ],
                [
                    372,
                    373
                ],
                [
                    378,
                    369
                ],
                [
                    386,
                    362
                ],
                [
                    390,
                    358
                ],
                [
                    395,
                    354
                ],
                [
                    400,
                    349
                ],
                [
                    405,
                    343
                ],
                [
                    406,
                    336
                ],
                [
                    406,
                    332
                ],
                [
                    403,
                    329
                ],
                [
                    398,
                    328
                ],
                [
                    392,
                    327
                ],
                [
                    381,
                    322
                ],
                [
                    373,
                    321
                ],
                [
                    368,
                    319
                ],
                [
                    360,
                    316
                ],
                [
                    356,
                    313
                ],
                [
                    351,
                    310
                ],
                [
                    345,
                    306
                ],
                [
                    337,
                    300
                ],
                [
                    332,
                    295
                ],
                [
                    329,
                    291
                ],
                [
                    321,
                    282
                ],
                [
                    317,
                    279
                ],
                [
                    313,
                    277
                ],
                [
                    310,
                    275
                ],
                [
                    308,
                    281
                ],
                [
                    308,
                    289
                ],
                [
                    310,
                    297
                ],
                [
                    311,
                    305
                ],
                [
                    311,
                    311
                ],
                [
                    311,
                    318
                ],
                [
                    309,
                    332
                ],
                [
                    309,
                    335
                ],
                [
                    309,
                    338
                ],
                [
                    308,
                    345
                ],
                [
                    307,
                    351
                ],
                [
                    305,
                    355
                ],
                [
                    303,
                    361
                ],
                [
                    301,
                    368
                ],
                [
                    300,
                    373
                ],
                [
                    296,
                    381
                ],
                [
                    294,
                    383
                ],
                [
                    288,
                    387
                ],
                [
                    279,
                    388
                ],
                [
                    272,
                    387
                ],
                [
                    261,
                    383
                ],
                [
                    267,
                    390
                ],
                [
                    267,
                    390
                ]
            ],
            "area": 7470.5,
            "layer": 8.0,
            "bbox": [
                261.0,
                275.0,
                406.0,
                400.0
            ],
            "iscrowd": 0,
            "note": ""
        },
        {
            "category": "S",
            "group": "",
            "segmentation": [
                [
                    250,
                    178
                ],
                [
                    247,
                    179
                ],
                [
                    245,
                    180
                ],
                [
                    242,
                    183
                ],
                [
                    237,
                    185
                ],
                [
                    232,
                    188
                ],
                [
                    229,
                    191
                ],
                [
                    226,
                    193
                ],
                [
                    225,
                    193
                ],
                [
                    224,
                    194
                ],
                [
                    220,
                    199
                ],
                [
                    218,
                    202
                ],
                [
                    216,
                    205
                ],
                [
                    214,
                    209
                ],
                [
                    211,
                    215
                ],
                [
                    210,
                    218
                ],
                [
                    209,
                    222
                ],
                [
                    208,
                    226
                ],
                [
                    208,
                    238
                ],
                [
                    209,
                    242
                ],
                [
                    210,
                    244
                ],
                [
                    212,
                    246
                ],
                [
                    212,
                    247
                ],
                [
                    213,
                    248
                ],
                [
                    215,
                    250
                ],
                [
                    218,
                    253
                ],
                [
                    224,
                    256
                ],
                [
                    227,
                    257
                ],
                [
                    232,
                    258
                ],
                [
                    238,
                    258
                ],
                [
                    244,
                    256
                ],
                [
                    265,
                    256
                ],
                [
                    269,
                    257
                ],
                [
                    276,
                    260
                ],
                [
                    281,
                    261
                ],
                [
                    290,
                    261
                ],
                [
                    293,
                    260
                ],
                [
                    296,
                    259
                ],
                [
                    303,
                    255
                ],
                [
                    305,
                    253
                ],
                [
                    307,
                    251
                ],
                [
                    310,
                    247
                ],
                [
                    311,
                    245
                ],
                [
                    312,
                    243
                ],
                [
                    312,
                    224
                ],
                [
                    311,
                    217
                ],
                [
                    310,
                    213
                ],
                [
                    309,
                    210
                ],
                [
                    305,
                    200
                ],
                [
                    303,
                    197
                ],
                [
                    298,
                    192
                ],
                [
                    292,
                    187
                ],
                [
                    290,
                    186
                ],
                [
                    283,
                    184
                ],
                [
                    276,
                    180
                ],
                [
                    273,
                    179
                ],
                [
                    270,
                    178
                ]
            ],
            "area": 6941.5,
            "layer": 9.0,
            "bbox": [
                208.0,
                178.0,
                312.0,
                261.0
            ],
            "iscrowd": 0,
            "note": ""
        }
    ]
}